[
  {
    "line": 1,
    "elements": [
      {
        "line": 4,
        "name": "Test smoke scenario",
        "description": "",
        "id": "test-smoke-macys;test-smoke-scenario",
        "type": "scenario",
        "keyword": "Scenario",
        "steps": [
          {
            "result": {
              "status": "undefined"
            },
            "line": 5,
            "name": "I open chrome browser",
            "match": {},
            "keyword": "Given "
          },
          {
            "result": {
              "status": "undefined"
            },
            "line": 6,
            "name": "I type macys website",
            "match": {},
            "keyword": "And "
          },
          {
            "result": {
              "status": "undefined"
            },
            "line": 7,
            "name": "I verify shop by department button",
            "match": {},
            "keyword": "When "
          },
          {
            "result": {
              "status": "undefined"
            },
            "line": 8,
            "name": "I close the browser",
            "match": {},
            "keyword": "Then "
          }
        ],
        "tags": [
          {
            "line": 3,
            "name": "@tag1"
          }
        ]
      }
    ],
    "name": "Test smoke macys",
    "description": "",
    "id": "test-smoke-macys",
    "keyword": "Feature",
    "uri": "SmokeMacys.feature"
  }
]